feagi_agent_video_capture/__init__.py
feagi_agent_video_capture/__main__.py
feagi_agent_video_capture/configuration.py
feagi_agent_video_capture/controller.py
feagi_agent_video_capture/version.py
feagi_agent_video_capture-0.0.13.dist-info/LICENSE
feagi_agent_video_capture-0.0.13.dist-info/METADATA
feagi_agent_video_capture-0.0.13.dist-info/WHEEL
feagi_agent_video_capture-0.0.13.dist-info/top_level.txt
feagi_agent_video_capture-0.0.13.dist-info/RECORD
